<?xml version="1.0" encoding="UTF-8" standalone="no"?>
<embeddedFont belowBaseline="4" fontName="OpenSans-Regular.ttf" size="12" yAdvance="19">
  <blockMappings>
    <blockMapping>BASIC_LATIN</blockMapping>
    <blockMapping>LATIN_EXTENDED_A</blockMapping>
    <blockMapping>CYRILLIC</blockMapping>
  </blockMappings>
  <glyphs>
    <glyph aboveBase="1" belowBase="0" code="31" height="1" selected="true" startX="0" startY="1" width="1" xAdvance="10">AA==</glyph>
    <glyph aboveBase="1" belowBase="0" code="32" height="1" selected="true" startX="0" startY="1" width="1" xAdvance="4">AA==</glyph>
    <glyph aboveBase="12" belowBase="0" code="33" height="12" selected="true" startX="1" startY="12" width="2" xAdvance="4">9VUP</glyph>
    <glyph aboveBase="4" belowBase="0" code="34" height="4" selected="true" startX="1" startY="12" width="5" xAdvance="7">3OUg</glyph>
    <glyph aboveBase="12" belowBase="0" code="35" height="12" selected="true" startX="0" startY="12" width="11" xAdvance="11">CIEQJD/xECIER/4SBECIEQA=</glyph>
    <glyph aboveBase="12" belowBase="1" code="36" height="13" selected="true" startX="1" startY="12" width="8" xAdvance="10">EH7SkNBwHhMTlvwQEA==</glyph>
    <glyph aboveBase="12" belowBase="0" code="37" height="12" selected="true" startX="1" startY="12" width="12" xAdvance="14">cEkIiYiQiuiplRdRCRGREJMO</glyph>
    <glyph aboveBase="12" belowBase="0" code="38" height="12" selected="true" startX="1" startY="12" width="11" xAdvance="12">PAzBCDMDwHAbFjKD0DMPPjA=</glyph>
    <glyph aboveBase="4" belowBase="0" code="39" height="4" selected="true" startX="1" startY="12" width="2" xAdvance="4">6g==</glyph>
    <glyph aboveBase="12" belowBase="3" code="40" height="15" selected="true" startX="1" startY="12" width="4" xAdvance="5">JkyIiIiMRiA=</glyph>
    <glyph aboveBase="12" belowBase="3" code="41" height="15" selected="true" startX="1" startY="12" width="3" xAdvance="5">mTJJJLWg</glyph>
    <glyph aboveBase="8" belowBase="0" code="42" height="8" selected="true" startX="1" startY="13" width="8" xAdvance="9">EBAQ/xgobEQ=</glyph>
    <glyph aboveBase="9" belowBase="0" code="43" height="9" selected="true" startX="1" startY="10" width="8" xAdvance="10">EBAQEP8QEBAQ</glyph>
    <glyph aboveBase="2" belowBase="2" code="44" height="4" selected="true" startX="1" startY="2" width="2" xAdvance="4">+g==</glyph>
    <glyph aboveBase="1" belowBase="0" code="45" height="1" selected="true" startX="1" startY="5" width="4" xAdvance="5">8A==</glyph>
    <glyph aboveBase="2" belowBase="0" code="46" height="2" selected="true" startX="1" startY="2" width="2" xAdvance="4">8A==</glyph>
    <glyph aboveBase="12" belowBase="0" code="47" height="12" selected="true" startX="0" startY="12" width="6" xAdvance="6">BCCGEEMIYQQw</glyph>
    <glyph aboveBase="12" belowBase="0" code="48" height="12" selected="true" startX="1" startY="12" width="8" xAdvance="10">PGbCg4ODg4ODwmY8</glyph>
    <glyph aboveBase="12" belowBase="0" code="49" height="12" selected="true" startX="2" startY="12" width="4" xAdvance="10">P5ERERER</glyph>
    <glyph aboveBase="12" belowBase="0" code="50" height="12" selected="true" startX="1" startY="12" width="8" xAdvance="10">fMYCAgIGDBgwYMD/</glyph>
    <glyph aboveBase="12" belowBase="0" code="51" height="12" selected="true" startX="1" startY="12" width="8" xAdvance="10">fMYCAgY8BgMDA4b8</glyph>
    <glyph aboveBase="12" belowBase="0" code="52" height="12" selected="true" startX="0" startY="12" width="9" xAdvance="10">AwODwWExGYyG/4GAwGA=</glyph>
    <glyph aboveBase="12" belowBase="0" code="53" height="12" selected="true" startX="1" startY="12" width="8" xAdvance="10">fkBAQED8BgMDA4b8</glyph>
    <glyph aboveBase="12" belowBase="0" code="54" height="12" selected="true" startX="1" startY="12" width="8" xAdvance="10">HjBAwMC8woOBw2Y8</glyph>
    <glyph aboveBase="12" belowBase="0" code="55" height="12" selected="true" startX="1" startY="12" width="8" xAdvance="10">/wMCBgQMCBgYEDAg</glyph>
    <glyph aboveBase="12" belowBase="0" code="56" height="12" selected="true" startX="1" startY="12" width="8" xAdvance="10">PEbCwmY4bsODg8J8</glyph>
    <glyph aboveBase="12" belowBase="0" code="57" height="12" selected="true" startX="1" startY="12" width="8" xAdvance="10">PMaCg4PHewMCBgx4</glyph>
    <glyph aboveBase="9" belowBase="0" code="58" height="9" selected="true" startX="1" startY="9" width="2" xAdvance="4">8APA</glyph>
    <glyph aboveBase="9" belowBase="2" code="59" height="11" selected="true" startX="1" startY="9" width="2" xAdvance="4">8APo</glyph>
    <glyph aboveBase="8" belowBase="0" code="60" height="8" selected="true" startX="1" startY="10" width="8" xAdvance="10">AQYYYMA4DgE=</glyph>
    <glyph aboveBase="4" belowBase="0" code="61" height="4" selected="true" startX="1" startY="8" width="8" xAdvance="10">/wAA/w==</glyph>
    <glyph aboveBase="8" belowBase="0" code="62" height="8" selected="true" startX="1" startY="10" width="8" xAdvance="10">gOAYBgMcYIA=</glyph>
    <glyph aboveBase="12" belowBase="0" code="63" height="12" selected="true" startX="0" startY="12" width="7" xAdvance="7">fIwIMEMEGAAAwYA=</glyph>
    <glyph aboveBase="12" belowBase="2" code="64" height="14" selected="true" startX="1" startY="12" width="13" xAdvance="15">D8DDCASPvMjERmIzEZiMStHcgAMED8A=</glyph>
    <glyph aboveBase="12" belowBase="0" code="65" height="12" selected="true" startX="0" startY="12" width="11" xAdvance="11">BAHAKA0BMCIIYfxgiBkBYDA=</glyph>
    <glyph aboveBase="12" belowBase="0" code="66" height="12" selected="true" startX="2" startY="12" width="8" xAdvance="11">/IaDg4b8goOBg4b8</glyph>
    <glyph aboveBase="12" belowBase="0" code="67" height="12" selected="true" startX="1" startY="12" width="9" xAdvance="11">H5hYGAwGAwGAwDAMI/A=</glyph>
    <glyph aboveBase="12" belowBase="0" code="68" height="12" selected="true" startX="2" startY="12" width="9" xAdvance="12">/EOgUDgMBgMBgcCh34A=</glyph>
    <glyph aboveBase="12" belowBase="0" code="69" height="12" selected="true" startX="2" startY="12" width="6" xAdvance="9">/gggg/ggggg/</glyph>
    <glyph aboveBase="12" belowBase="0" code="70" height="12" selected="true" startX="2" startY="12" width="6" xAdvance="9">/ggggg/ggggg</glyph>
    <glyph aboveBase="12" belowBase="0" code="71" height="12" selected="true" startX="1" startY="12" width="10" xAdvance="12">H4w2AwDAMAw/AcBYEwR/</glyph>
    <glyph aboveBase="12" belowBase="0" code="72" height="12" selected="true" startX="2" startY="12" width="9" xAdvance="13">gcDgcDgf/gcDgcDgcDA=</glyph>
    <glyph aboveBase="12" belowBase="0" code="73" height="12" selected="true" startX="2" startY="12" width="1" xAdvance="5">//A=</glyph>
    <glyph aboveBase="12" belowBase="3" code="74" height="15" selected="true" startX="-1" startY="12" width="4" xAdvance="5">ERERERERE+A=</glyph>
    <glyph aboveBase="12" belowBase="0" code="75" height="12" selected="true" startX="2" startY="12" width="8" xAdvance="10">g4aMmLCw0JiMhoKD</glyph>
    <glyph aboveBase="12" belowBase="0" code="76" height="12" selected="true" startX="2" startY="12" width="6" xAdvance="9">ggggggggggg/</glyph>
    <glyph aboveBase="12" belowBase="0" code="77" height="12" selected="true" startX="2" startY="12" width="12" xAdvance="15">wHwH4HoLoLkbkTmTizijjjhD</glyph>
    <glyph aboveBase="12" belowBase="0" code="78" height="12" selected="true" startX="2" startY="12" width="9" xAdvance="13">wOB4NhkMxjMJhsHgcDA=</glyph>
    <glyph aboveBase="12" belowBase="0" code="79" height="12" selected="true" startX="1" startY="12" width="11" xAdvance="13">HwY5gWA8A4BwDgHAbAjHD4A=</glyph>
    <glyph aboveBase="12" belowBase="0" code="80" height="12" selected="true" startX="2" startY="12" width="7" xAdvance="10">/Q4MGDH+QIECBAA=</glyph>
    <glyph aboveBase="12" belowBase="3" code="81" height="15" selected="true" startX="1" startY="12" width="11" xAdvance="13">HwY5gWA8A4BwDgHAbAjHD4AwAwAw</glyph>
    <glyph aboveBase="12" belowBase="0" code="82" height="12" selected="true" startX="2" startY="12" width="8" xAdvance="11">/IaCgoKG+IiMhoKD</glyph>
    <glyph aboveBase="12" belowBase="0" code="83" height="12" selected="true" startX="1" startY="12" width="8" xAdvance="9">PsLAwMBwHAIDAob8</glyph>
    <glyph aboveBase="12" belowBase="0" code="84" height="12" selected="true" startX="0" startY="12" width="9" xAdvance="9">/4QCAQCAQCAQCAQCAQA=</glyph>
    <glyph aboveBase="12" belowBase="0" code="85" height="12" selected="true" startX="2" startY="12" width="9" xAdvance="12">gcDgcDgcDgcDgcD4x8A=</glyph>
    <glyph aboveBase="12" belowBase="0" code="86" height="12" selected="true" startX="0" startY="12" width="10" xAdvance="10">wNA0CYYhiEMwSBoHgMAw</glyph>
    <glyph aboveBase="12" belowBase="0" code="87" height="12" selected="true" startX="0" startY="12" width="15" xAdvance="16">wYKDBQ4bFjYkRMiJExo0FCg4UGDgwIA=</glyph>
    <glyph aboveBase="12" belowBase="0" code="88" height="12" selected="true" startX="0" startY="12" width="10" xAdvance="10">QJhCMEgeAwDAWDMIRBsC</glyph>
    <glyph aboveBase="12" belowBase="0" code="89" height="12" selected="true" startX="0" startY="12" width="10" xAdvance="10">wJBmEIwyBQDAIAgCAIAg</glyph>
    <glyph aboveBase="12" belowBase="0" code="90" height="12" selected="true" startX="1" startY="12" width="8" xAdvance="10">/wMGBAwYEDBgQMD/</glyph>
    <glyph aboveBase="12" belowBase="3" code="91" height="15" selected="true" startX="1" startY="12" width="4" xAdvance="6">/MzMzMzMzPA=</glyph>
    <glyph aboveBase="12" belowBase="0" code="92" height="12" selected="true" startX="0" startY="12" width="6" xAdvance="6">wQQYIMEEGCCB</glyph>
    <glyph aboveBase="12" belowBase="3" code="93" height="15" selected="true" startX="0" startY="12" width="4" xAdvance="6">8REREREREfA=</glyph>
    <glyph aboveBase="8" belowBase="0" code="94" height="8" selected="true" startX="1" startY="12" width="8" xAdvance="10">EBgoJERCwoE=</glyph>
    <glyph aboveBase="-2" belowBase="3" code="95" height="1" selected="true" startX="0" startY="-2" width="7" xAdvance="7">/g==</glyph>
    <glyph aboveBase="3" belowBase="0" code="96" height="3" selected="true" startX="1" startY="13" width="3" xAdvance="5">yIA=</glyph>
    <glyph aboveBase="9" belowBase="0" code="97" height="9" selected="true" startX="1" startY="9" width="7" xAdvance="9">fIwIF/hg43o=</glyph>
    <glyph aboveBase="13" belowBase="0" code="98" height="13" selected="true" startX="1" startY="13" width="8" xAdvance="10">wMDAwN7jwcHBwcHj3g==</glyph>
    <glyph aboveBase="9" belowBase="0" code="99" height="9" selected="true" startX="1" startY="9" width="7" xAdvance="8">PsMECBAwMDw=</glyph>
    <glyph aboveBase="13" belowBase="0" code="100" height="13" selected="true" startX="1" startY="13" width="8" xAdvance="10">AQEBAT1nw4GBgcNnPQ==</glyph>
    <glyph aboveBase="9" belowBase="0" code="101" height="9" selected="true" startX="1" startY="9" width="8" xAdvance="10">PGbCg/+AwGI+</glyph>
    <glyph aboveBase="13" belowBase="0" code="102" height="13" selected="true" startX="0" startY="13" width="6" xAdvance="6">HMII/IIIIIIIIA==</glyph>
    <glyph aboveBase="9" belowBase="4" code="103" height="13" selected="true" startX="0" startY="9" width="9" xAdvance="9">P7EQyGYh4IDAPyDweCfg</glyph>
    <glyph aboveBase="13" belowBase="0" code="104" height="13" selected="true" startX="1" startY="13" width="8" xAdvance="10">wMDAwN7jwcHBwcHBwQ==</glyph>
    <glyph aboveBase="13" belowBase="0" code="105" height="13" selected="true" startX="1" startY="13" width="2" xAdvance="4">8P//wA==</glyph>
    <glyph aboveBase="13" belowBase="4" code="106" height="17" selected="true" startX="-1" startY="13" width="4" xAdvance="4">MwAzMzMzMzPg</glyph>
    <glyph aboveBase="13" belowBase="0" code="107" height="13" selected="true" startX="1" startY="13" width="8" xAdvance="9">wMDAwMbMyNDw2MzGwg==</glyph>
    <glyph aboveBase="13" belowBase="0" code="108" height="13" selected="true" startX="1" startY="13" width="2" xAdvance="4">////wA==</glyph>
    <glyph aboveBase="9" belowBase="0" code="109" height="9" selected="true" startX="1" startY="9" width="13" xAdvance="16">3Pcc8MOGHDDhhww4YcMI</glyph>
    <glyph aboveBase="9" belowBase="0" code="110" height="9" selected="true" startX="1" startY="9" width="8" xAdvance="10">3uPBwcHBwcHB</glyph>
    <glyph aboveBase="9" belowBase="0" code="111" height="9" selected="true" startX="1" startY="9" width="8" xAdvance="10">PGLDgYGBw2I8</glyph>
    <glyph aboveBase="9" belowBase="4" code="112" height="13" selected="true" startX="1" startY="9" width="8" xAdvance="10">3uPBwcHBwePewMDAwA==</glyph>
    <glyph aboveBase="9" belowBase="4" code="113" height="13" selected="true" startX="1" startY="9" width="8" xAdvance="10">PWfDgYGBw2c9AQEBAQ==</glyph>
    <glyph aboveBase="9" belowBase="0" code="114" height="9" selected="true" startX="1" startY="9" width="6" xAdvance="7">34wwwwwwwA==</glyph>
    <glyph aboveBase="9" belowBase="0" code="115" height="9" selected="true" startX="1" startY="9" width="6" xAdvance="8">fxg4ODBh+A==</glyph>
    <glyph aboveBase="11" belowBase="0" code="116" height="11" selected="true" startX="0" startY="11" width="6" xAdvance="6">II/IIIIIIIPA</glyph>
    <glyph aboveBase="9" belowBase="0" code="117" height="9" selected="true" startX="1" startY="9" width="8" xAdvance="10">wcHBwcHBw0c9</glyph>
    <glyph aboveBase="9" belowBase="0" code="118" height="9" selected="true" startX="0" startY="9" width="8" xAdvance="8">wUNDYiY0NBwY</glyph>
    <glyph aboveBase="9" belowBase="0" code="119" height="9" selected="true" startX="0" startY="9" width="13" xAdvance="13">wxo40UTKJtsUUKKHHBBg</glyph>
    <glyph aboveBase="9" belowBase="0" code="120" height="9" selected="true" startX="0" startY="9" width="9" xAdvance="9">QxENg4CAoNjEQQA=</glyph>
    <glyph aboveBase="9" belowBase="4" code="121" height="13" selected="true" startX="0" startY="9" width="9" xAdvance="9">wSGQzEJhoFA4GAwEBg4A</glyph>
    <glyph aboveBase="9" belowBase="0" code="122" height="9" selected="true" startX="1" startY="9" width="6" xAdvance="8">/DCEMIQw/A==</glyph>
    <glyph aboveBase="12" belowBase="3" code="123" height="15" selected="true" startX="0" startY="12" width="6" xAdvance="6">DEEEEEMwMEEEEEDA</glyph>
    <glyph aboveBase="13" belowBase="4" code="124" height="17" selected="true" startX="4" startY="13" width="1" xAdvance="9">//+A</glyph>
    <glyph aboveBase="12" belowBase="3" code="125" height="15" selected="true" startX="1" startY="12" width="5" xAdvance="6">wxjGMIMjGMYzAA==</glyph>
    <glyph aboveBase="2" belowBase="0" code="126" height="2" selected="true" startX="1" startY="7" width="8" xAdvance="10">8Y4=</glyph>
    <glyph aboveBase="14" belowBase="0" code="256" height="14" selected="true" startX="0" startY="14" width="11" xAdvance="11">HwAAEAcAoDQEwIghh/GCIGQFgMA=</glyph>
    <glyph aboveBase="11" belowBase="0" code="257" height="11" selected="true" startX="1" startY="11" width="7" xAdvance="9">PgHyMCBf4YON6A==</glyph>
    <glyph aboveBase="15" belowBase="0" code="258" height="15" selected="true" startX="0" startY="15" width="11" xAdvance="11">EQPAAAIA4BQGgJgRBDD+MEQMgLAY</glyph>
    <glyph aboveBase="12" belowBase="0" code="259" height="12" selected="true" startX="1" startY="12" width="7" xAdvance="9">IngD5GBAv8MHG9A=</glyph>
    <glyph aboveBase="12" belowBase="4" code="260" height="16" selected="true" startX="0" startY="12" width="11" xAdvance="11">BAHAKA0BMCIIYfxgiBkBYDAEAQAgBg==</glyph>
    <glyph aboveBase="9" belowBase="4" code="261" height="13" selected="true" startX="1" startY="9" width="7" xAdvance="9">fIwIF/hg43oEECBg</glyph>
    <glyph aboveBase="16" belowBase="0" code="262" height="16" selected="true" startX="1" startY="16" width="9" xAdvance="11">AwEBAAH5hYGAwGAwGAwDAMI/</glyph>
    <glyph aboveBase="13" belowBase="0" code="263" height="13" selected="true" startX="1" startY="13" width="7" xAdvance="8">DBBAA+wwQIEDAwPA</glyph>
    <glyph aboveBase="16" belowBase="0" code="264" height="16" selected="true" startX="1" startY="16" width="9" xAdvance="11">DAUEQAH5hYGAwGAwGAwDAMI/</glyph>
    <glyph aboveBase="13" belowBase="0" code="265" height="13" selected="true" startX="1" startY="13" width="7" xAdvance="8">MFEQA+wwQIEDAwPA</glyph>
    <glyph aboveBase="16" belowBase="0" code="266" height="16" selected="true" startX="1" startY="16" width="9" xAdvance="11">BAIAAAH5hYGAwGAwGAwDAMI/</glyph>
    <glyph aboveBase="13" belowBase="0" code="267" height="13" selected="true" startX="1" startY="13" width="7" xAdvance="8">ECAAA+wwQIEDAwPA</glyph>
    <glyph aboveBase="16" belowBase="0" code="268" height="16" selected="true" startX="1" startY="16" width="9" xAdvance="11">EQUDAAH5hYGAwGAwGAwDAMI/</glyph>
    <glyph aboveBase="13" belowBase="0" code="269" height="13" selected="true" startX="1" startY="13" width="7" xAdvance="8">RFDAA+wwQIEDAwPA</glyph>
    <glyph aboveBase="16" belowBase="0" code="270" height="16" selected="true" startX="2" startY="16" width="9" xAdvance="12">IgoGAA/EOgUDgMBgMBgcCh34</glyph>
    <glyph aboveBase="13" belowBase="0" code="271" height="13" selected="true" startX="1" startY="13" width="10" xAdvance="10">AUBQGAQ9GcwyBIEgTDGcPQA=</glyph>
    <glyph aboveBase="12" belowBase="0" code="272" height="12" selected="true" startX="0" startY="12" width="11" xAdvance="12">PwQ4gRAyAkB/CQEgZAiHH4A=</glyph>
    <glyph aboveBase="13" belowBase="0" code="273" height="13" selected="true" startX="1" startY="13" width="9" xAdvance="10">AQCH4CPTOw0CgUCwzOPQ</glyph>
    <glyph aboveBase="14" belowBase="0" code="274" height="14" selected="true" startX="2" startY="14" width="6" xAdvance="9">fA/gggg/ggggg/A=</glyph>
    <glyph aboveBase="11" belowBase="0" code="275" height="11" selected="true" startX="1" startY="11" width="8" xAdvance="10">PgA8ZsKD/4DAYj4=</glyph>
    <glyph aboveBase="15" belowBase="0" code="276" height="15" selected="true" startX="2" startY="15" width="6" xAdvance="9">ReA/gggg/ggggg/A</glyph>
    <glyph aboveBase="12" belowBase="0" code="277" height="12" selected="true" startX="1" startY="12" width="8" xAdvance="10">IjwAPGbCg/+AwGI+</glyph>
    <glyph aboveBase="16" belowBase="0" code="278" height="16" selected="true" startX="2" startY="16" width="6" xAdvance="9">EEAA/gggg/ggggg/</glyph>
    <glyph aboveBase="13" belowBase="0" code="279" height="13" selected="true" startX="1" startY="13" width="8" xAdvance="10">EBAAADxmwoP/gMBiPg==</glyph>
    <glyph aboveBase="12" belowBase="4" code="280" height="16" selected="true" startX="2" startY="12" width="6" xAdvance="9">/gggg/ggggg/BCCD</glyph>
    <glyph aboveBase="9" belowBase="4" code="281" height="13" selected="true" startX="1" startY="9" width="8" xAdvance="10">PGbCg/+AwGI+BAQMBg==</glyph>
    <glyph aboveBase="16" belowBase="0" code="282" height="16" selected="true" startX="2" startY="16" width="6" xAdvance="9">RKMA/gggg/ggggg/</glyph>
    <glyph aboveBase="13" belowBase="0" code="283" height="13" selected="true" startX="1" startY="13" width="8" xAdvance="10">RCgwADxmwoP/gMBiPg==</glyph>
    <glyph aboveBase="16" belowBase="0" code="284" height="16" selected="true" startX="1" startY="16" width="10" xAdvance="12">DAKBEAAfjDYDAMAwDD8BwFgTBH8=</glyph>
    <glyph aboveBase="13" belowBase="4" code="285" height="17" selected="true" startX="0" startY="13" width="9" xAdvance="9">GAoIgAP7EQyGYh4IDAPyDweCfgA=</glyph>
    <glyph aboveBase="15" belowBase="0" code="286" height="15" selected="true" startX="1" startY="15" width="10" xAdvance="12">CIPAAH4w2AwDAMAw/AcBYEwR/A==</glyph>
    <glyph aboveBase="12" belowBase="4" code="287" height="16" selected="true" startX="0" startY="12" width="9" xAdvance="9">Ih4AB/YiGQzEPBAYB+QeDwT8</glyph>
    <glyph aboveBase="16" belowBase="0" code="288" height="16" selected="true" startX="1" startY="16" width="10" xAdvance="12">BAEAAAAfjDYDAMAwDD8BwFgTBH8=</glyph>
    <glyph aboveBase="12" belowBase="4" code="289" height="16" selected="true" startX="0" startY="12" width="9" xAdvance="9">CAQAB/YiGQzEPBAYB+QeDwT8</glyph>
    <glyph aboveBase="12" belowBase="4" code="290" height="16" selected="true" startX="1" startY="12" width="10" xAdvance="12">H4w2AwDAMAw/AcBYEwR/AACAYBA=</glyph>
    <glyph aboveBase="13" belowBase="4" code="291" height="17" selected="true" startX="0" startY="13" width="9" xAdvance="9">CAQGAAP7EQyGYh4IDAPyDweCfgA=</glyph>
    <glyph aboveBase="16" belowBase="0" code="292" height="16" selected="true" startX="2" startY="16" width="9" xAdvance="13">GAoIgAgcDgcDgf/gcDgcDgcD</glyph>
    <glyph aboveBase="17" belowBase="0" code="293" height="17" selected="true" startX="0" startY="17" width="9" xAdvance="10">YCgiAAYDAYDAbzjYLBYLBYLBYIA=</glyph>
    <glyph aboveBase="12" belowBase="0" code="294" height="12" selected="true" startX="0" startY="12" width="13" xAdvance="13">IGEDP/5AwgYf8IGEDCBhAwgYQMA=</glyph>
    <glyph aboveBase="13" belowBase="0" code="295" height="13" selected="true" startX="0" startY="13" width="9" xAdvance="10">YDA/DAbzjYLBYLBYLBYI</glyph>
    <glyph aboveBase="15" belowBase="0" code="296" height="15" selected="true" startX="0" startY="15" width="6" xAdvance="5">5mAIIIIIIIIIIIIA</glyph>
    <glyph aboveBase="12" belowBase="0" code="297" height="12" selected="true" startX="-1" startY="12" width="6" xAdvance="4">5mAMMMMMMMMM</glyph>
    <glyph aboveBase="14" belowBase="0" code="298" height="14" selected="true" startX="0" startY="14" width="5" xAdvance="5">+AhCEIQhCEIQ</glyph>
    <glyph aboveBase="11" belowBase="0" code="299" height="11" selected="true" startX="0" startY="11" width="5" xAdvance="4">+BjGMYxjGA==</glyph>
    <glyph aboveBase="15" belowBase="0" code="300" height="15" selected="true" startX="0" startY="15" width="5" xAdvance="5">j4BCEIQhCEIQgA==</glyph>
    <glyph aboveBase="12" belowBase="0" code="301" height="12" selected="true" startX="0" startY="12" width="5" xAdvance="4">j4DGMYxjGMA=</glyph>
    <glyph aboveBase="12" belowBase="4" code="302" height="16" selected="true" startX="1" startY="12" width="2" xAdvance="5">VVVVaw==</glyph>
    <glyph aboveBase="13" belowBase="4" code="303" height="17" selected="true" startX="1" startY="13" width="2" xAdvance="4">8P//2sA=</glyph>
    <glyph aboveBase="16" belowBase="0" code="304" height="16" selected="true" startX="2" startY="16" width="1" xAdvance="5">z/8=</glyph>
    <glyph aboveBase="9" belowBase="0" code="305" height="9" selected="true" startX="1" startY="9" width="2" xAdvance="4">///A</glyph>
    <glyph aboveBase="12" belowBase="3" code="306" height="15" selected="true" startX="2" startY="12" width="6" xAdvance="9">hhhhhhhhhhhhBDOA</glyph>
    <glyph aboveBase="13" belowBase="4" code="307" height="17" selected="true" startX="1" startY="13" width="6" xAdvance="9">zzAAzzzzzzzzzDDDOA==</glyph>
    <glyph aboveBase="16" belowBase="3" code="308" height="19" selected="true" startX="-1" startY="16" width="6" xAdvance="5">MKRAEEEEEEEEEEEEEM4A</glyph>
    <glyph aboveBase="13" belowBase="4" code="309" height="17" selected="true" startX="-1" startY="13" width="6" xAdvance="4">MKRAMMMMMMMMMMMM4A==</glyph>
    <glyph aboveBase="12" belowBase="4" code="310" height="16" selected="true" startX="2" startY="12" width="8" xAdvance="10">g4aMmLCw0JiMhoKDABAwIA==</glyph>
    <glyph aboveBase="13" belowBase="4" code="311" height="17" selected="true" startX="1" startY="13" width="8" xAdvance="9">wMDAwMbMyNDw2MzGwgAQMCA=</glyph>
    <glyph aboveBase="9" belowBase="0" code="312" height="9" selected="true" startX="1" startY="9" width="8" xAdvance="9">xsTI0PDIzMbC</glyph>
    <glyph aboveBase="16" belowBase="0" code="313" height="16" selected="true" startX="2" startY="16" width="6" xAdvance="9">YQgAggggggggggg/</glyph>
    <glyph aboveBase="17" belowBase="0" code="314" height="17" selected="true" startX="1" startY="17" width="4" xAdvance="4">MkDMzMzMzMzA</glyph>
    <glyph aboveBase="12" belowBase="4" code="315" height="16" selected="true" startX="2" startY="12" width="6" xAdvance="9">ggggggggggg/AEMI</glyph>
    <glyph aboveBase="13" belowBase="4" code="316" height="17" selected="true" startX="1" startY="13" width="2" xAdvance="4">////x4A=</glyph>
    <glyph aboveBase="12" belowBase="0" code="317" height="12" selected="true" startX="2" startY="12" width="6" xAdvance="9">hhigggggggg/</glyph>
    <glyph aboveBase="13" belowBase="0" code="318" height="13" selected="true" startX="1" startY="13" width="4" xAdvance="4">3ezMzMzMwA==</glyph>
    <glyph aboveBase="12" belowBase="0" code="319" height="12" selected="true" startX="2" startY="12" width="6" xAdvance="9">ggggiiggggg/</glyph>
    <glyph aboveBase="13" belowBase="0" code="320" height="13" selected="true" startX="1" startY="13" width="4" xAdvance="4">zMzN3MzMwA==</glyph>
    <glyph aboveBase="12" belowBase="0" code="321" height="12" selected="true" startX="0" startY="12" width="8" xAdvance="9">ICAgICQ8MOAgICA/</glyph>
    <glyph aboveBase="13" belowBase="0" code="322" height="13" selected="true" startX="0" startY="13" width="4" xAdvance="4">ZmZnfuZmYA==</glyph>
    <glyph aboveBase="16" belowBase="0" code="323" height="16" selected="true" startX="2" startY="16" width="9" xAdvance="13">BgICAAwOB4NhkMxjMJhsHgcD</glyph>
    <glyph aboveBase="13" belowBase="0" code="324" height="13" selected="true" startX="1" startY="13" width="8" xAdvance="10">BgQIAN7jwcHBwcHBwQ==</glyph>
    <glyph aboveBase="12" belowBase="4" code="325" height="16" selected="true" startX="2" startY="12" width="9" xAdvance="13">wOB4NhkMxjMJhsHgcDAAQGAg</glyph>
    <glyph aboveBase="9" belowBase="4" code="326" height="13" selected="true" startX="1" startY="9" width="8" xAdvance="10">3uPBwcHBwcHBAAgYEA==</glyph>
    <glyph aboveBase="16" belowBase="0" code="327" height="16" selected="true" startX="2" startY="16" width="9" xAdvance="13">IgoGAAwOB4NhkMxjMJhsHgcD</glyph>
    <glyph aboveBase="13" belowBase="0" code="328" height="13" selected="true" startX="1" startY="13" width="8" xAdvance="10">IhQYAN7jwcHBwcHBwQ==</glyph>
    <glyph aboveBase="12" belowBase="0" code="329" height="12" selected="true" startX="0" startY="12" width="10" xAdvance="12">YBAEAt44zBMEwTBMEwTB</glyph>
    <glyph aboveBase="12" belowBase="3" code="330" height="15" selected="true" startX="2" startY="12" width="9" xAdvance="13">wOB4NhkMxjMJhsHgcDAIDBw=</glyph>
    <glyph aboveBase="9" belowBase="4" code="331" height="13" selected="true" startX="1" startY="9" width="8" xAdvance="10">3uPBwcHBwcHBAQEDDg==</glyph>
    <glyph aboveBase="14" belowBase="0" code="332" height="14" selected="true" startX="1" startY="14" width="11" xAdvance="13">HwAAfBjmBYDwDgHAOAcBsCMcPgA=</glyph>
    <glyph aboveBase="11" belowBase="0" code="333" height="11" selected="true" startX="1" startY="11" width="8" xAdvance="10">PgA8YsOBgYHDYjw=</glyph>
    <glyph aboveBase="15" belowBase="0" code="334" height="15" selected="true" startX="1" startY="15" width="11" xAdvance="13">EQPAAA+DHMCwHgHAOAcA4DYEY4fA</glyph>
    <glyph aboveBase="12" belowBase="0" code="335" height="12" selected="true" startX="1" startY="12" width="8" xAdvance="10">IjwAPGLDgYGBw2I8</glyph>
    <glyph aboveBase="16" belowBase="0" code="336" height="16" selected="true" startX="1" startY="16" width="11" xAdvance="13">BoGwJAAB8GOYFgPAOAcA4BwGwIxw+A==</glyph>
    <glyph aboveBase="13" belowBase="0" code="337" height="13" selected="true" startX="1" startY="13" width="8" xAdvance="10">GjYkADxiw4GBgcNiPA==</glyph>
    <glyph aboveBase="12" belowBase="0" code="338" height="12" selected="true" startX="1" startY="12" width="14" xAdvance="16">H/zGBhgwYMGDB+wYMGDBgYYDGAf/</glyph>
    <glyph aboveBase="9" belowBase="0" code="339" height="9" selected="true" startX="1" startY="9" width="14" xAdvance="16">PHmaPDBgQYH+BAwwGaE8fA==</glyph>
    <glyph aboveBase="16" belowBase="0" code="340" height="16" selected="true" startX="2" startY="16" width="8" xAdvance="11">DAgQAPyGgoKChviIjIaCgw==</glyph>
    <glyph aboveBase="13" belowBase="0" code="341" height="13" selected="true" startX="1" startY="13" width="6" xAdvance="7">GEIA34wwwwwwwA==</glyph>
    <glyph aboveBase="12" belowBase="4" code="342" height="16" selected="true" startX="2" startY="12" width="8" xAdvance="11">/IaCgoKG+IiMhoKDABAwIA==</glyph>
    <glyph aboveBase="9" belowBase="4" code="343" height="13" selected="true" startX="1" startY="9" width="6" xAdvance="7">34wwwwwwwAQwgA==</glyph>
    <glyph aboveBase="16" belowBase="0" code="344" height="16" selected="true" startX="2" startY="16" width="8" xAdvance="11">RCgwAPyGgoKChviIjIaCgw==</glyph>
    <glyph aboveBase="13" belowBase="0" code="345" height="13" selected="true" startX="1" startY="13" width="6" xAdvance="7">RKMA34wwwwwwwA==</glyph>
    <glyph aboveBase="16" belowBase="0" code="346" height="16" selected="true" startX="1" startY="16" width="8" xAdvance="9">DAgQAD7CwMDAcBwCAwKG/A==</glyph>
    <glyph aboveBase="13" belowBase="0" code="347" height="13" selected="true" startX="1" startY="13" width="6" xAdvance="8">GEIAfxg4ODBh+A==</glyph>
    <glyph aboveBase="16" belowBase="0" code="348" height="16" selected="true" startX="1" startY="16" width="8" xAdvance="9">MChEAD7CwMDAcBwCAwKG/A==</glyph>
    <glyph aboveBase="13" belowBase="0" code="349" height="13" selected="true" startX="1" startY="13" width="6" xAdvance="8">MKRAfxg4ODBh+A==</glyph>
    <glyph aboveBase="12" belowBase="4" code="350" height="16" selected="true" startX="1" startY="12" width="8" xAdvance="9">PsLAwMBwHAIDAob8EBgMOA==</glyph>
    <glyph aboveBase="9" belowBase="4" code="351" height="13" selected="true" startX="1" startY="9" width="6" xAdvance="8">fxg4ODBh+IMGcA==</glyph>
    <glyph aboveBase="16" belowBase="0" code="352" height="16" selected="true" startX="1" startY="16" width="8" xAdvance="9">RCgwAD7CwMDAcBwCAwKG/A==</glyph>
    <glyph aboveBase="13" belowBase="0" code="353" height="13" selected="true" startX="1" startY="13" width="6" xAdvance="8">RKMAfxg4ODBh+A==</glyph>
    <glyph aboveBase="12" belowBase="4" code="354" height="16" selected="true" startX="0" startY="12" width="9" xAdvance="9">/4QCAQCAQCAQCAQCAQCAYBg4</glyph>
    <glyph aboveBase="11" belowBase="4" code="355" height="15" selected="true" startX="0" startY="11" width="6" xAdvance="6">II/IIIIIIIPEGDOA</glyph>
    <glyph aboveBase="16" belowBase="0" code="356" height="16" selected="true" startX="0" startY="16" width="9" xAdvance="9">IgoGAA/4QCAQCAQCAQCAQCAQ</glyph>
    <glyph aboveBase="13" belowBase="0" code="357" height="13" selected="true" startX="0" startY="13" width="8" xAdvance="6">AQEiIPwgICAgICAgPA==</glyph>
    <glyph aboveBase="12" belowBase="0" code="358" height="12" selected="true" startX="0" startY="12" width="9" xAdvance="9">/4QCAQCD+CAQCAQCAQA=</glyph>
    <glyph aboveBase="11" belowBase="0" code="359" height="11" selected="true" startX="0" startY="11" width="6" xAdvance="6">II/II+IIIIPA</glyph>
    <glyph aboveBase="15" belowBase="0" code="360" height="15" selected="true" startX="2" startY="15" width="9" xAdvance="12">ciYAEDgcDgcDgcDgcDgfGPg=</glyph>
    <glyph aboveBase="12" belowBase="0" code="361" height="12" selected="true" startX="1" startY="12" width="8" xAdvance="10">ckwAwcHBwcHBw0c9</glyph>
    <glyph aboveBase="14" belowBase="0" code="362" height="14" selected="true" startX="2" startY="14" width="9" xAdvance="12">PgAgcDgcDgcDgcDgcD4x8A==</glyph>
    <glyph aboveBase="11" belowBase="0" code="363" height="11" selected="true" startX="1" startY="11" width="8" xAdvance="10">PgDBwcHBwcHDRz0=</glyph>
    <glyph aboveBase="15" belowBase="0" code="364" height="15" selected="true" startX="2" startY="15" width="9" xAdvance="12">Ih4AEDgcDgcDgcDgcDgfGPg=</glyph>
    <glyph aboveBase="12" belowBase="0" code="365" height="12" selected="true" startX="1" startY="12" width="8" xAdvance="10">IjwAwcHBwcHBw0c9</glyph>
    <glyph aboveBase="17" belowBase="0" code="366" height="17" selected="true" startX="2" startY="17" width="9" xAdvance="12">HAoFA4AEDgcDgcDgcDgcDgfGPgA=</glyph>
    <glyph aboveBase="14" belowBase="0" code="367" height="14" selected="true" startX="1" startY="14" width="8" xAdvance="10">HBQUHADBwcHBwcHDRz0=</glyph>
    <glyph aboveBase="16" belowBase="0" code="368" height="16" selected="true" startX="2" startY="16" width="9" xAdvance="12">GhsJAAgcDgcDgcDgcDgcD4x8</glyph>
    <glyph aboveBase="13" belowBase="0" code="369" height="13" selected="true" startX="1" startY="13" width="8" xAdvance="10">GjYkAMHBwcHBwcNHPQ==</glyph>
    <glyph aboveBase="12" belowBase="4" code="370" height="16" selected="true" startX="2" startY="12" width="9" xAdvance="12">gcDgcDgcDgcDgcD4x8BAIBAM</glyph>
    <glyph aboveBase="9" belowBase="4" code="371" height="13" selected="true" startX="1" startY="9" width="8" xAdvance="10">wcHBwcHBw0c9AQICAw==</glyph>
    <glyph aboveBase="16" belowBase="0" code="372" height="16" selected="true" startX="0" startY="16" width="15" xAdvance="16">AwAFABEAAAwYKDBQ4bFjYkRMiJExo0FCg4UGDgwI</glyph>
    <glyph aboveBase="13" belowBase="0" code="373" height="13" selected="true" startX="0" startY="13" width="13" xAdvance="13">BgAoAiAADDGjjRRMom2xRQooccEGAA==</glyph>
    <glyph aboveBase="16" belowBase="0" code="374" height="16" selected="true" startX="0" startY="16" width="10" xAdvance="10">GAUCIADAkGYQjDIFAMAgCAIAgCA=</glyph>
    <glyph aboveBase="13" belowBase="4" code="375" height="17" selected="true" startX="0" startY="13" width="9" xAdvance="9">GAoIgAwSGQzEJhoFA4GAwEBg4AA=</glyph>
    <glyph aboveBase="16" belowBase="0" code="376" height="16" selected="true" startX="0" startY="16" width="10" xAdvance="10">EgSAAADAkGYQjDIFAMAgCAIAgCA=</glyph>
    <glyph aboveBase="16" belowBase="0" code="377" height="16" selected="true" startX="1" startY="16" width="8" xAdvance="10">DAgQAP8DBgQMGBAwYEDA/w==</glyph>
    <glyph aboveBase="13" belowBase="0" code="378" height="13" selected="true" startX="1" startY="13" width="6" xAdvance="8">GEIA/DCEMIQw/A==</glyph>
    <glyph aboveBase="16" belowBase="0" code="379" height="16" selected="true" startX="1" startY="16" width="8" xAdvance="10">EBAAAP8DBgQMGBAwYEDA/w==</glyph>
    <glyph aboveBase="13" belowBase="0" code="380" height="13" selected="true" startX="1" startY="13" width="6" xAdvance="8">EEAA/DCEMIQw/A==</glyph>
    <glyph aboveBase="16" belowBase="0" code="381" height="16" selected="true" startX="1" startY="16" width="8" xAdvance="10">RCgwAP8DBgQMGBAwYEDA/w==</glyph>
    <glyph aboveBase="13" belowBase="0" code="382" height="13" selected="true" startX="1" startY="13" width="6" xAdvance="8">RKMA/DCEMIQw/A==</glyph>
    <glyph aboveBase="16" belowBase="0" code="1024" height="16" selected="true" startX="2" startY="16" width="6" xAdvance="9">YIEA/gggg/ggggg/</glyph>
    <glyph aboveBase="16" belowBase="0" code="1025" height="16" selected="true" startX="2" startY="16" width="6" xAdvance="9">SSAA/gggg/ggggg/</glyph>
    <glyph aboveBase="12" belowBase="0" code="1026" height="12" selected="true" startX="0" startY="12" width="11" xAdvance="12">/wIAQAgBAD+EGIEQIgRBiOA=</glyph>
    <glyph aboveBase="16" belowBase="0" code="1027" height="16" selected="true" startX="2" startY="16" width="6" xAdvance="9">DCEA/ggggggggggg</glyph>
    <glyph aboveBase="12" belowBase="0" code="1028" height="12" selected="true" startX="1" startY="12" width="9" xAdvance="11">H5hYGAwH+wGAwDAMI/A=</glyph>
    <glyph aboveBase="12" belowBase="0" code="1029" height="12" selected="true" startX="1" startY="12" width="8" xAdvance="9">PsLAwMBwHAIDAob8</glyph>
    <glyph aboveBase="12" belowBase="0" code="1030" height="12" selected="true" startX="2" startY="12" width="1" xAdvance="5">//A=</glyph>
    <glyph aboveBase="16" belowBase="0" code="1031" height="16" selected="true" startX="0" startY="16" width="4" xAdvance="5">mQAiIiIiIiI=</glyph>
    <glyph aboveBase="12" belowBase="3" code="1032" height="15" selected="true" startX="-1" startY="12" width="4" xAdvance="5">ERERERERE+A=</glyph>
    <glyph aboveBase="12" belowBase="0" code="1033" height="12" selected="true" startX="0" startY="12" width="15" xAdvance="16">D4ARAGIAxAGIAh8EI4hBMIJhBII/B8A=</glyph>
    <glyph aboveBase="12" belowBase="0" code="1034" height="12" selected="true" startX="2" startY="12" width="14" xAdvance="16">gwIMCDAgwIMD/8gxoMODDgwoMaD8</glyph>
    <glyph aboveBase="12" belowBase="0" code="1035" height="12" selected="true" startX="0" startY="12" width="11" xAdvance="12">/4IAQAgBAD+EGIEQIgRAiBA=</glyph>
    <glyph aboveBase="16" belowBase="0" code="1036" height="16" selected="true" startX="2" startY="16" width="8" xAdvance="10">DAgQAIOGjJiw4KCQmIyGgw==</glyph>
    <glyph aboveBase="16" belowBase="0" code="1037" height="16" selected="true" startX="2" startY="16" width="9" xAdvance="13">GAQBAAgcDg8NhMZmMhsPBwOB</glyph>
    <glyph aboveBase="16" belowBase="0" code="1038" height="16" selected="true" startX="0" startY="16" width="11" xAdvance="11">IQZgeAAMBMGIIYwRAyAsBwBgGAYDgA==</glyph>
    <glyph aboveBase="12" belowBase="3" code="1039" height="15" selected="true" startX="2" startY="12" width="9" xAdvance="12">gcDgcDgcDgcDgcDgf/GAwGA=</glyph>
    <glyph aboveBase="12" belowBase="0" code="1040" height="12" selected="true" startX="0" startY="12" width="11" xAdvance="11">BAHAKA0BMCIIYfxgiBkBYDA=</glyph>
    <glyph aboveBase="12" belowBase="0" code="1041" height="12" selected="true" startX="2" startY="12" width="7" xAdvance="10">/wIECB+hwYMGH+A=</glyph>
    <glyph aboveBase="12" belowBase="0" code="1042" height="12" selected="true" startX="2" startY="12" width="8" xAdvance="11">/IaDg4b8goOBg4b8</glyph>
    <glyph aboveBase="12" belowBase="0" code="1043" height="12" selected="true" startX="2" startY="12" width="6" xAdvance="9">/ggggggggggg</glyph>
    <glyph aboveBase="12" belowBase="3" code="1044" height="15" selected="true" startX="0" startY="12" width="11" xAdvance="12">D8EYIwRhjDGEMIYwxBmDf/gDAGAI</glyph>
    <glyph aboveBase="12" belowBase="0" code="1045" height="12" selected="true" startX="2" startY="12" width="6" xAdvance="9">/gggg/ggggg/</glyph>
    <glyph aboveBase="12" belowBase="0" code="1046" height="12" selected="true" startX="0" startY="12" width="14" xAdvance="14">Qw2MYzMGyAtAHwD8AtgTIMxGMbDD</glyph>
    <glyph aboveBase="12" belowBase="0" code="1047" height="12" selected="true" startX="1" startY="12" width="8" xAdvance="10">fMYDAwZ8BgMBA4b8</glyph>
    <glyph aboveBase="12" belowBase="0" code="1048" height="12" selected="true" startX="2" startY="12" width="9" xAdvance="13">gcDg8NhMZmMhsPBwOBA=</glyph>
    <glyph aboveBase="16" belowBase="0" code="1049" height="16" selected="true" startX="2" startY="16" width="9" xAdvance="13">IRmHgAgcDg8NhMZmMhsPBwOB</glyph>
    <glyph aboveBase="12" belowBase="0" code="1050" height="12" selected="true" startX="2" startY="12" width="8" xAdvance="10">g4aMmLDgoJCYjIaD</glyph>
    <glyph aboveBase="12" belowBase="0" code="1051" height="12" selected="true" startX="0" startY="12" width="10" xAdvance="12">D8IRhGEYRBEEQTBMEgeB</glyph>
    <glyph aboveBase="12" belowBase="0" code="1052" height="12" selected="true" startX="2" startY="12" width="12" xAdvance="15">wHwH4HoLoLkbkTmTizijjjhD</glyph>
    <glyph aboveBase="12" belowBase="0" code="1053" height="12" selected="true" startX="2" startY="12" width="9" xAdvance="13">gcDgcDgf/gcDgcDgcDA=</glyph>
    <glyph aboveBase="12" belowBase="0" code="1054" height="12" selected="true" startX="1" startY="12" width="11" xAdvance="13">HwY5gWA8A4BwDgHAbAjHD4A=</glyph>
    <glyph aboveBase="12" belowBase="0" code="1055" height="12" selected="true" startX="2" startY="12" width="9" xAdvance="12">/8DgcDgcDgcDgcDgcDA=</glyph>
    <glyph aboveBase="12" belowBase="0" code="1056" height="12" selected="true" startX="2" startY="12" width="7" xAdvance="10">/Q4MGDH+QIECBAA=</glyph>
    <glyph aboveBase="12" belowBase="0" code="1057" height="12" selected="true" startX="1" startY="12" width="9" xAdvance="11">H5hYGAwGAwGAwDAMI/A=</glyph>
    <glyph aboveBase="12" belowBase="0" code="1058" height="12" selected="true" startX="0" startY="12" width="9" xAdvance="9">/4QCAQCAQCAQCAQCAQA=</glyph>
    <glyph aboveBase="12" belowBase="0" code="1059" height="12" selected="true" startX="0" startY="12" width="11" xAdvance="11">wEwYghjBEDICwHAGAYBgOAA=</glyph>
    <glyph aboveBase="12" belowBase="0" code="1060" height="12" selected="true" startX="1" startY="12" width="12" xAdvance="14">BABAP4ZGxChDhDxCZGP4BABA</glyph>
    <glyph aboveBase="12" belowBase="0" code="1061" height="12" selected="true" startX="0" startY="12" width="10" xAdvance="10">QJhCMEgeAwDAWDMIRBsC</glyph>
    <glyph aboveBase="12" belowBase="3" code="1062" height="15" selected="true" startX="2" startY="12" width="10" xAdvance="13">gaBoGgaBoGgaBoGgaBv/AEAQBA==</glyph>
    <glyph aboveBase="12" belowBase="0" code="1063" height="12" selected="true" startX="1" startY="12" width="9" xAdvance="12">wOBwOBwOBY59AIBAIBA=</glyph>
    <glyph aboveBase="12" belowBase="0" code="1064" height="12" selected="true" startX="2" startY="12" width="14" xAdvance="18">gg4IOCDgg4IOCDgg4IOCDgg4IP//</glyph>
    <glyph aboveBase="12" belowBase="3" code="1065" height="15" selected="true" startX="2" startY="12" width="15" xAdvance="18">gg0EGgg0EGgg0EGgg0EGgg0EGgg3//AAIABAAIA=</glyph>
    <glyph aboveBase="12" belowBase="0" code="1066" height="12" selected="true" startX="0" startY="12" width="11" xAdvance="12">8AIAQAgBAD8EMIMQYgxDD8A=</glyph>
    <glyph aboveBase="12" belowBase="0" code="1067" height="12" selected="true" startX="2" startY="12" width="11" xAdvance="14">gHAOAcA4B/jhnBOCcE4Z/jA=</glyph>
    <glyph aboveBase="12" belowBase="0" code="1068" height="12" selected="true" startX="2" startY="12" width="8" xAdvance="11">gICAgID8hoODg4b8</glyph>
    <glyph aboveBase="12" belowBase="0" code="1069" height="12" selected="true" startX="1" startY="12" width="9" xAdvance="11">/EMAwCAb/AYDAQGDn4A=</glyph>
    <glyph aboveBase="12" belowBase="0" code="1070" height="12" selected="true" startX="2" startY="12" width="15" xAdvance="18">gfEOMhA0YCjAf4DjAcYDjAUIGgxkD4A=</glyph>
    <glyph aboveBase="12" belowBase="0" code="1071" height="12" selected="true" startX="0" startY="12" width="9" xAdvance="11">H5hYLBYJhH4xEJhYKBA=</glyph>
    <glyph aboveBase="9" belowBase="0" code="1072" height="9" selected="true" startX="1" startY="9" width="7" xAdvance="9">fIwIF/hg43o=</glyph>
    <glyph aboveBase="13" belowBase="0" code="1073" height="13" selected="true" startX="1" startY="13" width="8" xAdvance="10">BzxgQMDeo8GBwcNiPA==</glyph>
    <glyph aboveBase="9" belowBase="0" code="1074" height="9" selected="true" startX="1" startY="9" width="8" xAdvance="10">/sPDwvzDwcP+</glyph>
    <glyph aboveBase="9" belowBase="0" code="1075" height="9" selected="true" startX="1" startY="9" width="6" xAdvance="7">/wwwwwwwwA==</glyph>
    <glyph aboveBase="9" belowBase="3" code="1076" height="12" selected="true" startX="0" startY="9" width="9" xAdvance="10">HwyEQiERiITC/+BwOBA=</glyph>
    <glyph aboveBase="9" belowBase="0" code="1077" height="9" selected="true" startX="1" startY="9" width="8" xAdvance="10">PGbCg/+AwGI+</glyph>
    <glyph aboveBase="9" belowBase="0" code="1078" height="9" selected="true" startX="0" startY="9" width="12" xAdvance="13">QjImEsGoDwGoMkYiwjA=</glyph>
    <glyph aboveBase="9" belowBase="0" code="1079" height="9" selected="true" startX="1" startY="9" width="6" xAdvance="8">+jBDeBBD+A==</glyph>
    <glyph aboveBase="9" belowBase="0" code="1080" height="9" selected="true" startX="1" startY="9" width="8" xAdvance="11">w8PFzcnR8eHB</glyph>
    <glyph aboveBase="13" belowBase="0" code="1081" height="13" selected="true" startX="1" startY="13" width="8" xAdvance="11">ITMeAMPDxc3J0fHhwQ==</glyph>
    <glyph aboveBase="9" belowBase="0" code="1082" height="9" selected="true" startX="1" startY="9" width="8" xAdvance="9">xszI0ODQyMTC</glyph>
    <glyph aboveBase="9" belowBase="0" code="1083" height="9" selected="true" startX="0" startY="9" width="8" xAdvance="10">HxERETExIWHB</glyph>
    <glyph aboveBase="9" belowBase="0" code="1084" height="9" selected="true" startX="1" startY="9" width="10" xAdvance="12">wPg+F8XTdJynMcxA</glyph>
    <glyph aboveBase="9" belowBase="0" code="1085" height="9" selected="true" startX="1" startY="9" width="8" xAdvance="11">wcHBwf/BwcHB</glyph>
    <glyph aboveBase="9" belowBase="0" code="1086" height="9" selected="true" startX="1" startY="9" width="8" xAdvance="10">PGLDgYGBw2I8</glyph>
    <glyph aboveBase="9" belowBase="0" code="1087" height="9" selected="true" startX="1" startY="9" width="8" xAdvance="11">/8HBwcHBwcHB</glyph>
    <glyph aboveBase="9" belowBase="4" code="1088" height="13" selected="true" startX="1" startY="9" width="8" xAdvance="10">3uPBwcHBwePewMDAwA==</glyph>
    <glyph aboveBase="9" belowBase="0" code="1089" height="9" selected="true" startX="1" startY="9" width="7" xAdvance="8">PsMECBAwMDw=</glyph>
    <glyph aboveBase="9" belowBase="0" code="1090" height="9" selected="true" startX="0" startY="9" width="8" xAdvance="8">/xgYGBgYGBgY</glyph>
    <glyph aboveBase="9" belowBase="4" code="1091" height="13" selected="true" startX="0" startY="9" width="9" xAdvance="9">wSGQzEJhoFA4GAwEBg4A</glyph>
    <glyph aboveBase="13" belowBase="4" code="1092" height="17" selected="true" startX="1" startY="13" width="10" xAdvance="12">DAMAwDA/G2zOMYxjHM22PwMAwDAMAA==</glyph>
    <glyph aboveBase="9" belowBase="0" code="1093" height="9" selected="true" startX="0" startY="9" width="9" xAdvance="9">QxENg4CAoNjEQQA=</glyph>
    <glyph aboveBase="9" belowBase="3" code="1094" height="12" selected="true" startX="1" startY="9" width="9" xAdvance="11">wWCwWCwWCwWC/4BAIBA=</glyph>
    <glyph aboveBase="9" belowBase="0" code="1095" height="9" selected="true" startX="1" startY="9" width="8" xAdvance="10">w8PDw8d7AwMD</glyph>
    <glyph aboveBase="9" belowBase="0" code="1096" height="9" selected="true" startX="1" startY="9" width="13" xAdvance="15">wh4Q8IeEPCHhDwh4Q//4</glyph>
    <glyph aboveBase="9" belowBase="3" code="1097" height="12" selected="true" startX="1" startY="9" width="14" xAdvance="15">whsIbCGwhsIbCGwhsIb//AAQAEAB</glyph>
    <glyph aboveBase="9" belowBase="0" code="1098" height="9" selected="true" startX="0" startY="9" width="11" xAdvance="12">+AMAYAwB/DDGGMMfwA==</glyph>
    <glyph aboveBase="9" belowBase="0" code="1099" height="9" selected="true" startX="1" startY="9" width="11" xAdvance="13">wHgPAeA/54bw3hv+YA==</glyph>
    <glyph aboveBase="9" belowBase="0" code="1100" height="9" selected="true" startX="1" startY="9" width="8" xAdvance="10">wMDAwP7DwcP+</glyph>
    <glyph aboveBase="9" belowBase="0" code="1101" height="9" selected="true" startX="1" startY="9" width="6" xAdvance="8">8DBB/BBD8A==</glyph>
    <glyph aboveBase="9" belowBase="0" code="1102" height="9" selected="true" startX="1" startY="9" width="12" xAdvance="14">w8xixDzB/BzBxDxiw8A=</glyph>
    <glyph aboveBase="9" belowBase="0" code="1103" height="9" selected="true" startX="0" startY="9" width="8" xAdvance="9">P2FBYT8xIWFB</glyph>
    <glyph aboveBase="13" belowBase="0" code="1104" height="13" selected="true" startX="1" startY="13" width="8" xAdvance="10">MBAIADxmwoP/gMBiPg==</glyph>
    <glyph aboveBase="13" belowBase="0" code="1105" height="13" selected="true" startX="1" startY="13" width="8" xAdvance="10">JCQAADxmwoP/gMBiPg==</glyph>
    <glyph aboveBase="13" belowBase="4" code="1106" height="17" selected="true" startX="0" startY="13" width="9" xAdvance="10">YDA/DAbzjYLBYLBYLBYIBAIDAwA=</glyph>
    <glyph aboveBase="13" belowBase="0" code="1107" height="13" selected="true" startX="1" startY="13" width="6" xAdvance="7">DCEA/wwwwwwwwA==</glyph>
    <glyph aboveBase="9" belowBase="0" code="1108" height="9" selected="true" startX="1" startY="9" width="7" xAdvance="8">PsMED9AwMT4=</glyph>
    <glyph aboveBase="9" belowBase="0" code="1109" height="9" selected="true" startX="1" startY="9" width="6" xAdvance="8">fxg4ODBh+A==</glyph>
    <glyph aboveBase="13" belowBase="0" code="1110" height="13" selected="true" startX="1" startY="13" width="2" xAdvance="4">8P//wA==</glyph>
    <glyph aboveBase="13" belowBase="0" code="1111" height="13" selected="true" startX="0" startY="13" width="4" xAdvance="4">mQBmZmZmYA==</glyph>
    <glyph aboveBase="13" belowBase="4" code="1112" height="17" selected="true" startX="-1" startY="13" width="4" xAdvance="4">MwAzMzMzMzPg</glyph>
    <glyph aboveBase="9" belowBase="0" code="1113" height="9" selected="true" startX="0" startY="9" width="13" xAdvance="14">HwCYBMAmAz8ZjIwsY8Pw</glyph>
    <glyph aboveBase="9" belowBase="0" code="1114" height="9" selected="true" startX="1" startY="9" width="13" xAdvance="15">wwYYMMGGD/9hhww4Y8Pw</glyph>
    <glyph aboveBase="13" belowBase="0" code="1115" height="13" selected="true" startX="0" startY="13" width="9" xAdvance="10">YDA/DAbzjYLBYLBYLBYI</glyph>
    <glyph aboveBase="13" belowBase="0" code="1116" height="13" selected="true" startX="1" startY="13" width="8" xAdvance="9">DAgQAMbMyNDg0MjEwg==</glyph>
    <glyph aboveBase="13" belowBase="0" code="1117" height="13" selected="true" startX="1" startY="13" width="8" xAdvance="11">GAgEAMPDxc3J0fHhwQ==</glyph>
    <glyph aboveBase="13" belowBase="4" code="1118" height="17" selected="true" startX="0" startY="13" width="9" xAdvance="9">QjMPAAwSGQzEJhoFA4GAwEBg4AA=</glyph>
    <glyph aboveBase="9" belowBase="3" code="1119" height="12" selected="true" startX="1" startY="9" width="8" xAdvance="11">wcHBwcHBwcH/CAgI</glyph>
    <glyph aboveBase="12" belowBase="0" code="1120" height="12" selected="true" startX="0" startY="12" width="15" xAdvance="16">wQKCBQYKDDYYbHCIsRFiNkwo0HDgYYA=</glyph>
    <glyph aboveBase="9" belowBase="0" code="1121" height="9" selected="true" startX="0" startY="9" width="13" xAdvance="13">wh4Q0IaGJjESmJaHHBjA</glyph>
    <glyph aboveBase="12" belowBase="0" code="1122" height="12" selected="true" startX="0" startY="12" width="11" xAdvance="11">EAID/AgBAD8EMIIQYghDD8A=</glyph>
    <glyph aboveBase="11" belowBase="0" code="1123" height="11" selected="true" startX="0" startY="11" width="10" xAdvance="11">MAwPwMAwDAP4wzDMM/g=</glyph>
    <glyph aboveBase="12" belowBase="0" code="1124" height="12" selected="true" startX="2" startY="12" width="13" xAdvance="16">gfwY4YEYCMB/8jARgIwEMCDDA/A=</glyph>
    <glyph aboveBase="9" belowBase="0" code="1125" height="9" selected="true" startX="1" startY="9" width="11" xAdvance="13">w/jHEGYP/ZgxBjHD4A==</glyph>
    <glyph aboveBase="12" belowBase="0" code="1126" height="12" selected="true" startX="0" startY="12" width="11" xAdvance="11">BgHAKAWBED8NISZkSIkR4hA=</glyph>
    <glyph aboveBase="9" belowBase="0" code="1127" height="9" selected="true" startX="0" startY="9" width="9" xAdvance="10">DA4FhkPhWaSTyIA=</glyph>
    <glyph aboveBase="12" belowBase="0" code="1128" height="12" selected="true" startX="2" startY="12" width="14" xAdvance="16">gYIGCDwgkIZj/4jaI2yJkmZpGKxi</glyph>
    <glyph aboveBase="9" belowBase="0" code="1129" height="9" selected="true" startX="1" startY="9" width="12" xAdvance="13">www4xoxM/8yUyW2S0TA=</glyph>
    <glyph aboveBase="12" belowBase="0" code="1130" height="12" selected="true" startX="0" startY="12" width="12" xAdvance="12">f+IGEMCYDwH4NkJmZiRiRjxj</glyph>
    <glyph aboveBase="9" belowBase="0" code="1131" height="9" selected="true" startX="0" startY="9" width="11" xAdvance="11">f8QwRAUD8EkZMiLEQA==</glyph>
    <glyph aboveBase="12" belowBase="0" code="1132" height="12" selected="true" startX="2" startY="12" width="15" xAdvance="17">j/kYMhhEEQgUH/4jJkREiIkxGkIUhCA=</glyph>
    <glyph aboveBase="9" belowBase="0" code="1133" height="9" selected="true" startX="1" startY="9" width="13" xAdvance="14">z/ZhMZmHj/5m2yZbM9GI</glyph>
    <glyph aboveBase="14" belowBase="3" code="1134" height="17" selected="true" startX="1" startY="14" width="8" xAdvance="10">Zjh8xgMDBngGAwMDBvyAgP8=</glyph>
    <glyph aboveBase="11" belowBase="3" code="1135" height="14" selected="true" startX="0" startY="11" width="7" xAdvance="8">ZnHwMCDPAQIF9gwPwA==</glyph>
    <glyph aboveBase="12" belowBase="0" code="1136" height="12" selected="true" startX="1" startY="12" width="12" xAdvance="14">hDhDhDhDhDxCZOP4BABABABA</glyph>
    <glyph aboveBase="13" belowBase="4" code="1137" height="17" selected="true" startX="1" startY="13" width="11" xAdvance="13">BACAEAIMRYjxHiPEeI0RMmHwCAEAIAQA</glyph>
    <glyph aboveBase="12" belowBase="0" code="1138" height="12" selected="true" startX="1" startY="12" width="11" xAdvance="13">HwY5AWA8A//wDgHAbAjHD4A=</glyph>
    <glyph aboveBase="9" belowBase="0" code="1139" height="9" selected="true" startX="1" startY="9" width="8" xAdvance="10">PGLBgf+BwWI8</glyph>
    <glyph aboveBase="12" belowBase="0" code="1140" height="12" selected="true" startX="0" startY="12" width="11" xAdvance="11">wGgZAjDCEEIMwJAaA8AwBgA=</glyph>
    <glyph aboveBase="9" belowBase="0" code="1141" height="9" selected="true" startX="0" startY="9" width="9" xAdvance="9">waGQjEJhINA4GAA=</glyph>
    <glyph aboveBase="16" belowBase="0" code="1142" height="16" selected="true" startX="0" startY="16" width="11" xAdvance="11">bAbASAAMBoGQIwwhBCDMCQGgPAMAYA==</glyph>
    <glyph aboveBase="13" belowBase="0" code="1143" height="13" selected="true" startX="0" startY="13" width="9" xAdvance="9">2DYJAAwaGQjEJhINA4GA</glyph>
    <glyph aboveBase="12" belowBase="4" code="1144" height="16" selected="true" startX="1" startY="12" width="19" xAdvance="21">HwAOMAEDAGBsHASHgJCwExYCJsDGiBhRxg4PgYAAMAAEAAGAAOA=</glyph>
    <glyph aboveBase="9" belowBase="4" code="1145" height="13" selected="true" startX="1" startY="9" width="18" xAdvance="18">PGCYiGwyGgTEgRMgRowwoYg4PAwAAwAAgABgAHAA</glyph>
    <glyph aboveBase="13" belowBase="1" code="1146" height="14" selected="true" startX="1" startY="13" width="12" xAdvance="14">BgH4NsYGwCwDwDwDwDwCYGNsH4Bg</glyph>
    <glyph aboveBase="10" belowBase="1" code="1147" height="11" selected="true" startX="1" startY="10" width="9" xAdvance="11">CB8a2DgMBgODax8CAA==</glyph>
    <glyph aboveBase="18" belowBase="0" code="1148" height="18" selected="true" startX="1" startY="18" width="15" xAdvance="17">B4AJwAQACAAwAAAPHjAmQAeABwAMABwQOCBwQaCDc4w98A==</glyph>
    <glyph aboveBase="15" belowBase="0" code="1149" height="15" selected="true" startX="1" startY="15" width="13" xAdvance="15">DwBOAIAEAGAAAPPIA8AMAGCDhBwhs4z3gA==</glyph>
    <glyph aboveBase="15" belowBase="0" code="1150" height="15" selected="true" startX="0" startY="15" width="15" xAdvance="16">B+AKQAAGCBQQKDBQYbDDY4RFiIsRsmFGg4cDDAA=</glyph>
    <glyph aboveBase="12" belowBase="0" code="1151" height="12" selected="true" startX="0" startY="12" width="13" xAdvance="13">D8BSAAGEPCGhDQxMYiUxLQ44MYA=</glyph>
    <glyph aboveBase="12" belowBase="4" code="1152" height="16" selected="true" startX="1" startY="12" width="9" xAdvance="11">H5hYGAwGAwGAwDAMA8AgEAgE</glyph>
    <glyph aboveBase="9" belowBase="4" code="1153" height="13" selected="true" startX="1" startY="9" width="7" xAdvance="8">PsMECBAwMDwYMGDA</glyph>
    <glyph aboveBase="11" belowBase="0" code="1154" height="11" selected="true" startX="1" startY="11" width="8" xAdvance="10">AgIcDAuI0DAsZEA=</glyph>
    <glyph aboveBase="3" belowBase="0" code="1155" height="3" selected="false" startX="-8" startY="13" width="6" xAdvance="0">B/wA</glyph>
    <glyph aboveBase="2" belowBase="0" code="1156" height="2" selected="false" startX="-8" startY="12" width="6" xAdvance="0">H5A=</glyph>
    <glyph aboveBase="3" belowBase="0" code="1157" height="3" selected="false" startX="-6" startY="13" width="2" xAdvance="0">5A==</glyph>
    <glyph aboveBase="3" belowBase="0" code="1158" height="3" selected="false" startX="-6" startY="13" width="2" xAdvance="0">2A==</glyph>
    <glyph aboveBase="1" belowBase="0" code="1159" height="1" selected="true" startX="0" startY="1" width="1" xAdvance="10">AA==</glyph>
    <glyph aboveBase="12" belowBase="3" code="1160" height="15" selected="true" startX="0" startY="12" width="16" xAdvance="17">AcAAQBAMKBIAAAAAYAKQBQAAAAAAADgOAAABwABA</glyph>
    <glyph aboveBase="12" belowBase="3" code="1161" height="15" selected="true" startX="0" startY="12" width="16" xAdvance="16">AIAAgBGEEBgIAAAAAABgBwAAAAAAABgIMIgAgAEA</glyph>
    <glyph aboveBase="16" belowBase="3" code="1162" height="19" selected="true" startX="2" startY="16" width="11" xAdvance="13">YwRA8AAIGQMg5DSEkZJiSEsJwTAmBwBACAMA</glyph>
    <glyph aboveBase="13" belowBase="3" code="1163" height="16" selected="true" startX="1" startY="13" width="10" xAdvance="11">IwiB4ADDMMxTNMk0TxOEwcAgCAI=</glyph>
    <glyph aboveBase="12" belowBase="0" code="1164" height="12" selected="true" startX="0" startY="12" width="9" xAdvance="10">IBA/BAIB+IZBIJBIZ+A=</glyph>
    <glyph aboveBase="13" belowBase="0" code="1165" height="13" selected="true" startX="0" startY="13" width="9" xAdvance="10">IBA+BAIBAIBAPxDIJDPw</glyph>
    <glyph aboveBase="12" belowBase="0" code="1166" height="12" selected="true" startX="2" startY="12" width="7" xAdvance="10">/Q4MGTH/Q4ECBAA=</glyph>
    <glyph aboveBase="9" belowBase="4" code="1167" height="13" selected="true" startX="1" startY="9" width="8" xAdvance="10">3uPBwcHBzefewcDAwA==</glyph>
    <glyph aboveBase="15" belowBase="0" code="1168" height="15" selected="true" startX="2" startY="15" width="7" xAdvance="9">Bgwf+BAgQIECBAgQIAA=</glyph>
    <glyph aboveBase="12" belowBase="0" code="1169" height="12" selected="true" startX="1" startY="12" width="6" xAdvance="7">BBB/wwwwwwww</glyph>
    <glyph aboveBase="12" belowBase="0" code="1170" height="12" selected="true" startX="0" startY="12" width="9" xAdvance="9">P5AIBAIBA/hAIBAIBAA=</glyph>
    <glyph aboveBase="9" belowBase="0" code="1171" height="9" selected="true" startX="0" startY="9" width="7" xAdvance="7">fsGDD8wYMGA=</glyph>
    <glyph aboveBase="12" belowBase="4" code="1172" height="16" selected="true" startX="2" startY="12" width="8" xAdvance="11">/oCAgID8joOBgYGBAQMGPA==</glyph>
    <glyph aboveBase="9" belowBase="4" code="1173" height="13" selected="true" startX="1" startY="9" width="7" xAdvance="9">/YMGD9jw4cIECDPA</glyph>
    <glyph aboveBase="12" belowBase="3" code="1174" height="15" selected="true" startX="0" startY="12" width="15" xAdvance="15">QwzGMMzA2QC0APgD8AWwEyBmIYxmGHAAYADAAYA=</glyph>
    <glyph aboveBase="9" belowBase="3" code="1175" height="12" selected="true" startX="0" startY="9" width="13" xAdvance="13">QjETBLA1APANQMkMRMI4AEACABA=</glyph>
    <glyph aboveBase="12" belowBase="4" code="1176" height="16" selected="true" startX="1" startY="12" width="8" xAdvance="10">fMYDAwZ8BgMBA4b8EAgIOA==</glyph>
    <glyph aboveBase="9" belowBase="4" code="1177" height="13" selected="true" startX="1" startY="9" width="6" xAdvance="8">+jBDeBBD+IEEcA==</glyph>
    <glyph aboveBase="12" belowBase="3" code="1178" height="15" selected="true" startX="2" startY="12" width="9" xAdvance="11">g0MjEwsHAoEgmEYhkHAIBAI=</glyph>
    <glyph aboveBase="9" belowBase="3" code="1179" height="12" selected="true" startX="1" startY="9" width="8" xAdvance="9">xszI0ODQyMTDAQEB</glyph>
    <glyph aboveBase="12" belowBase="0" code="1180" height="12" selected="true" startX="2" startY="12" width="8" xAdvance="10">g4asuLDgoLC4rIaD</glyph>
    <glyph aboveBase="9" belowBase="0" code="1181" height="9" selected="true" startX="1" startY="9" width="8" xAdvance="9">xtzY0PDQ2NTC</glyph>
    <glyph aboveBase="12" belowBase="0" code="1182" height="12" selected="true" startX="0" startY="12" width="10" xAdvance="10">IP5iMJgsDgKAkCYIwhiD</glyph>
    <glyph aboveBase="13" belowBase="0" code="1183" height="13" selected="true" startX="0" startY="13" width="9" xAdvance="9">YDA/DAYzMZDQcDQZDEYQ</glyph>
    <glyph aboveBase="12" belowBase="0" code="1184" height="12" selected="true" startX="0" startY="12" width="12" xAdvance="12">8GEMEYEwEgHAFgEwEQEIEEEG</glyph>
    <glyph aboveBase="9" belowBase="0" code="1185" height="9" selected="true" startX="0" startY="9" width="10" xAdvance="10">+MZhsHgcB4GwZhjA</glyph>
    <glyph aboveBase="12" belowBase="3" code="1186" height="15" selected="true" startX="2" startY="12" width="10" xAdvance="13">gaBoGgaBv+gaBoGgaBoHAEAQBA==</glyph>
    <glyph aboveBase="9" belowBase="3" code="1187" height="12" selected="true" startX="1" startY="9" width="10" xAdvance="11">wTBMEwT/MEwTBMHAMAwD</glyph>
    <glyph aboveBase="12" belowBase="0" code="1188" height="12" selected="true" startX="2" startY="12" width="12" xAdvance="14">gfgYgYgYgY/4gYgYgYgYgYgY</glyph>
    <glyph aboveBase="9" belowBase="0" code="1189" height="9" selected="true" startX="1" startY="9" width="11" xAdvance="12">wfgjBGCP8YIwRgjBAA==</glyph>
    <glyph aboveBase="12" belowBase="4" code="1190" height="16" selected="true" startX="2" startY="12" width="15" xAdvance="18">/wECAgQECAgQED8gQ0CDgQMCBgQMCBAAIADAAwA8</glyph>
    <glyph aboveBase="9" belowBase="4" code="1191" height="13" selected="true" startX="1" startY="9" width="13" xAdvance="15">/wYYMMGGDD5hmwx4YcMIAEAGACAPAA==</glyph>
    <glyph aboveBase="12" belowBase="1" code="1192" height="13" selected="true" startX="1" startY="12" width="11" xAdvance="13">Hg4BAGHsZ4xxDiHGbEzPD8AO</glyph>
    <glyph aboveBase="9" belowBase="0" code="1193" height="9" selected="true" startX="1" startY="9" width="9" xAdvance="11">OCAx0biMTzTMP4A=</glyph>
    <glyph aboveBase="12" belowBase="4" code="1194" height="16" selected="true" startX="1" startY="12" width="9" xAdvance="11">H5hYGAwGAwGAwDAMI/BAEAgc</glyph>
    <glyph aboveBase="9" belowBase="4" code="1195" height="13" selected="true" startX="1" startY="9" width="7" xAdvance="8">PsMECBAwMDwgIEOA</glyph>
    <glyph aboveBase="12" belowBase="3" code="1196" height="15" selected="true" startX="0" startY="12" width="9" xAdvance="9">/4QCAQCAQCAQCAQCAcBgMBg=</glyph>
    <glyph aboveBase="9" belowBase="3" code="1197" height="12" selected="true" startX="0" startY="9" width="8" xAdvance="8">/xgYGBgYGBgcBAQE</glyph>
    <glyph aboveBase="12" belowBase="0" code="1198" height="12" selected="true" startX="0" startY="12" width="10" xAdvance="10">wJBmEIwyBQDAIAgCAIAg</glyph>
    <glyph aboveBase="9" belowBase="4" code="1199" height="13" selected="true" startX="0" startY="9" width="8" xAdvance="8">wUNCYiY0FBwYCAgICA==</glyph>
    <glyph aboveBase="12" belowBase="0" code="1200" height="12" selected="true" startX="0" startY="12" width="10" xAdvance="10">wJBmEIwyBwDAID8CAIAg</glyph>
    <glyph aboveBase="9" belowBase="4" code="1201" height="13" selected="true" startX="0" startY="9" width="8" xAdvance="8">wUNCYiY0FBwYfggICA==</glyph>
    <glyph aboveBase="12" belowBase="3" code="1202" height="15" selected="true" startX="0" startY="12" width="10" xAdvance="11">QJhCMEgeAwDAWDMIRBsDAEAQBA==</glyph>
    <glyph aboveBase="9" belowBase="3" code="1203" height="12" selected="true" startX="0" startY="9" width="9" xAdvance="9">QxENg4CAoNjGQYBAIBA=</glyph>
    <glyph aboveBase="12" belowBase="3" code="1204" height="15" selected="true" startX="0" startY="12" width="14" xAdvance="15">/5ggYIGCBggYIGCBggYIGCBggYP/AAQAEABA</glyph>
    <glyph aboveBase="9" belowBase="3" code="1205" height="12" selected="true" startX="0" startY="9" width="12" xAdvance="12">/mEGEGEGEGEGEGEGH/ABABAB</glyph>
    <glyph aboveBase="12" belowBase="3" code="1206" height="15" selected="true" startX="1" startY="12" width="11" xAdvance="12">wJgTAmBMCYEY4fQAgBACAHAGAMAY</glyph>
    <glyph aboveBase="9" belowBase="3" code="1207" height="12" selected="true" startX="1" startY="9" width="9" xAdvance="10">w2Gw2Gxz2AwGA4BAIBA=</glyph>
    <glyph aboveBase="12" belowBase="0" code="1208" height="12" selected="true" startX="1" startY="12" width="9" xAdvance="12">wOBwOByORa59CIRAIBA=</glyph>
    <glyph aboveBase="9" belowBase="0" code="1209" height="9" selected="true" startX="1" startY="9" width="8" xAdvance="10">w8PT09d7ExMD</glyph>
    <glyph aboveBase="12" belowBase="0" code="1210" height="12" selected="true" startX="2" startY="12" width="8" xAdvance="12">gICAgL7jgYGBgYGB</glyph>
    <glyph aboveBase="13" belowBase="0" code="1211" height="13" selected="true" startX="1" startY="13" width="8" xAdvance="10">wMDAwN7jwcHBwcHBwQ==</glyph>
    <glyph aboveBase="12" belowBase="0" code="1212" height="12" selected="true" startX="0" startY="12" width="13" xAdvance="14">A+BxggawFQC//EADABgAYAGEB+A=</glyph>
    <glyph aboveBase="9" belowBase="0" code="1213" height="9" selected="true" startX="0" startY="9" width="10" xAdvance="11">B4I9B0F/xAEAYQfA</glyph>
    <glyph aboveBase="12" belowBase="3" code="1214" height="15" selected="true" startX="0" startY="12" width="13" xAdvance="14">A+AxgwYwNYCoBf/iABgAQAOEB+AIAEACAA==</glyph>
    <glyph aboveBase="9" belowBase="3" code="1215" height="12" selected="true" startX="0" startY="9" width="10" xAdvance="11">B4I9B0F/xAEAYQfAgCAI</glyph>
    <glyph aboveBase="12" belowBase="0" code="1216" height="12" selected="true" startX="2" startY="12" width="1" xAdvance="5">//A=</glyph>
    <glyph aboveBase="16" belowBase="0" code="1217" height="16" selected="true" startX="0" startY="16" width="14" xAdvance="14">CEAzAHgAAEMNjGMzBsgLQB8A/ALYEyDMRjGwww==</glyph>
    <glyph aboveBase="13" belowBase="0" code="1218" height="13" selected="true" startX="0" startY="13" width="12" xAdvance="13">EIGYDwAAQjImEsGoDwGoMkYiwjA=</glyph>
    <glyph aboveBase="12" belowBase="4" code="1219" height="16" selected="true" startX="2" startY="12" width="9" xAdvance="12">g0MjEwkFA/EOgUDgcDAYCBx4</glyph>
    <glyph aboveBase="9" belowBase="4" code="1220" height="13" selected="true" startX="1" startY="9" width="8" xAdvance="9">xszY0PzGw8PDAwMmPA==</glyph>
    <glyph aboveBase="12" belowBase="3" code="1221" height="15" selected="true" startX="0" startY="12" width="12" xAdvance="12">D8CEGEGEGEEEEEEEMEMEIE4HACACAGA=</glyph>
    <glyph aboveBase="9" belowBase="3" code="1222" height="12" selected="true" startX="0" startY="9" width="10" xAdvance="10">HwRBEEQxDEIRhMHAIAgG</glyph>
    <glyph aboveBase="12" belowBase="4" code="1223" height="16" selected="true" startX="2" startY="12" width="9" xAdvance="12">gcDgcDgf/gcDgcDgcDAYCIx8</glyph>
    <glyph aboveBase="9" belowBase="4" code="1224" height="13" selected="true" startX="1" startY="9" width="8" xAdvance="11">wcHBwf/BwcHBAQETHg==</glyph>
    <glyph aboveBase="12" belowBase="3" code="1225" height="15" selected="true" startX="2" startY="12" width="10" xAdvance="13">gaBoGgaBv+gaBoGgaBoHAEAwCA==</glyph>
    <glyph aboveBase="9" belowBase="3" code="1226" height="12" selected="true" startX="1" startY="9" width="10" xAdvance="11">wTBMEwT/MEwTBMHAIAgG</glyph>
    <glyph aboveBase="12" belowBase="3" code="1227" height="15" selected="true" startX="1" startY="12" width="9" xAdvance="12">wOBwOBwOBY59AIBAIHAwGAw=</glyph>
    <glyph aboveBase="9" belowBase="3" code="1228" height="12" selected="true" startX="1" startY="9" width="8" xAdvance="10">w8PDw8d7AwMHBgYG</glyph>
    <glyph aboveBase="12" belowBase="3" code="1229" height="15" selected="true" startX="2" startY="12" width="13" xAdvance="15">wHYDuB1BagtI2kTTJos0UaONCHABgAgAQA==</glyph>
    <glyph aboveBase="9" belowBase="3" code="1230" height="12" selected="true" startX="1" startY="9" width="12" xAdvance="13">wM4M4U8U000kykzEzGACACAG</glyph>
    <glyph aboveBase="12" belowBase="0" code="1231" height="12" selected="true" startX="2" startY="12" width="1" xAdvance="5">//A=</glyph>
    <glyph aboveBase="16" belowBase="0" code="1232" height="16" selected="true" startX="0" startY="16" width="11" xAdvance="11">EIMwPAAAQBwCgNATAiCGH8YIgZAWAw==</glyph>
    <glyph aboveBase="13" belowBase="0" code="1233" height="13" selected="true" startX="1" startY="13" width="7" xAdvance="9">QszwB8jAgX+GDjeg</glyph>
    <glyph aboveBase="16" belowBase="0" code="1234" height="16" selected="true" startX="0" startY="16" width="11" xAdvance="11">EgJAAAAAQBwCgNATAiCGH8YIgZAWAw==</glyph>
    <glyph aboveBase="13" belowBase="0" code="1235" height="13" selected="true" startX="1" startY="13" width="7" xAdvance="9">JEgAB8jAgX+GDjeg</glyph>
    <glyph aboveBase="12" belowBase="0" code="1236" height="12" selected="true" startX="0" startY="12" width="14" xAdvance="15">B/wWANgCYAmAR/EYD+AhgYYEGDB/</glyph>
    <glyph aboveBase="9" belowBase="0" code="1237" height="9" selected="true" startX="1" startY="9" width="13" xAdvance="15">feI5gYYMN//jAhgZ4Hjw</glyph>
    <glyph aboveBase="16" belowBase="0" code="1238" height="16" selected="true" startX="2" startY="16" width="6" xAdvance="9">hzeA/gggg/ggggg/</glyph>
    <glyph aboveBase="13" belowBase="0" code="1239" height="13" selected="true" startX="1" startY="13" width="8" xAdvance="10">QmY8ADxmwoP/gMBiPg==</glyph>
    <glyph aboveBase="12" belowBase="0" code="1240" height="12" selected="true" startX="1" startY="12" width="10" xAdvance="12">fhDgDAMAQB//AcBQNhj4</glyph>
    <glyph aboveBase="9" belowBase="0" code="1241" height="9" selected="true" startX="1" startY="9" width="8" xAdvance="10">/IYCA/+DwkY8</glyph>
    <glyph aboveBase="16" belowBase="0" code="1242" height="16" selected="true" startX="1" startY="16" width="10" xAdvance="12">EgSAAAB+EOAMAwBAH/8BwFA2GPg=</glyph>
    <glyph aboveBase="13" belowBase="0" code="1243" height="13" selected="true" startX="1" startY="13" width="8" xAdvance="10">JCQAAPyGAgP/g8JGPA==</glyph>
    <glyph aboveBase="16" belowBase="0" code="1244" height="16" selected="true" startX="0" startY="16" width="14" xAdvance="14">BIASAAAAAEMNjGMzBsgLQB8A/ALYEyDMRjGwww==</glyph>
    <glyph aboveBase="13" belowBase="0" code="1245" height="13" selected="true" startX="0" startY="13" width="12" xAdvance="13">CQCQAAAAQjImEsGoDwGoMkYiwjA=</glyph>
    <glyph aboveBase="16" belowBase="0" code="1246" height="16" selected="true" startX="1" startY="16" width="8" xAdvance="10">JCQAAHzGAwMGfAYDAQOG/A==</glyph>
    <glyph aboveBase="13" belowBase="0" code="1247" height="13" selected="true" startX="1" startY="13" width="6" xAdvance="8">SSAA+jBDeBBD+A==</glyph>
    <glyph aboveBase="12" belowBase="0" code="1248" height="12" selected="true" startX="1" startY="12" width="8" xAdvance="10">/gYMGDA8BgMDA4b8</glyph>
    <glyph aboveBase="9" belowBase="4" code="1249" height="13" selected="true" startX="0" startY="9" width="8" xAdvance="8">/gYMGDA8BgMDAwKG/A==</glyph>
    <glyph aboveBase="14" belowBase="0" code="1250" height="14" selected="true" startX="2" startY="14" width="9" xAdvance="13">PgAgcDg8NhMZmMhsPBwOBA==</glyph>
    <glyph aboveBase="11" belowBase="0" code="1251" height="11" selected="true" startX="1" startY="11" width="8" xAdvance="11">PgDDw8XNydHx4cE=</glyph>
    <glyph aboveBase="16" belowBase="0" code="1252" height="16" selected="true" startX="2" startY="16" width="9" xAdvance="13">EgkAAAgcDg8NhMZmMhsPBwOB</glyph>
    <glyph aboveBase="13" belowBase="0" code="1253" height="13" selected="true" startX="1" startY="13" width="8" xAdvance="11">EhIAAMPDxc3J0fHhwQ==</glyph>
    <glyph aboveBase="16" belowBase="0" code="1254" height="16" selected="true" startX="1" startY="16" width="11" xAdvance="13">CQEgAAAB8GOYFgPAOAcA4BwGwIxw+A==</glyph>
    <glyph aboveBase="13" belowBase="0" code="1255" height="13" selected="true" startX="1" startY="13" width="8" xAdvance="10">JCQAADxiw4GBgcNiPA==</glyph>
    <glyph aboveBase="12" belowBase="0" code="1256" height="12" selected="true" startX="1" startY="12" width="11" xAdvance="13">HwY5AWA8A//wDgHAbAjHD4A=</glyph>
    <glyph aboveBase="9" belowBase="0" code="1257" height="9" selected="true" startX="1" startY="9" width="8" xAdvance="10">PGLBgf+BwWI8</glyph>
    <glyph aboveBase="16" belowBase="0" code="1258" height="16" selected="true" startX="1" startY="16" width="11" xAdvance="13">CQEgAAAB8GOQFgPAP/8A4BwGwIxw+A==</glyph>
    <glyph aboveBase="13" belowBase="0" code="1259" height="13" selected="true" startX="1" startY="13" width="8" xAdvance="10">JCQAADxiwYH/gcFiPA==</glyph>
    <glyph aboveBase="16" belowBase="0" code="1260" height="16" selected="true" startX="1" startY="16" width="9" xAdvance="11">JBIAAA/EMAwCAb/AYDAQGDn4</glyph>
    <glyph aboveBase="13" belowBase="0" code="1261" height="13" selected="true" startX="1" startY="13" width="6" xAdvance="8">SSAA8DBB/BBD8A==</glyph>
    <glyph aboveBase="14" belowBase="0" code="1262" height="14" selected="true" startX="0" startY="14" width="11" xAdvance="11">HwADATBiCGMEQMgLAcAYBgGA4AA=</glyph>
    <glyph aboveBase="11" belowBase="4" code="1263" height="15" selected="true" startX="0" startY="11" width="9" xAdvance="9">PgAwSGQzEJhoFA4GAwEBg4A=</glyph>
    <glyph aboveBase="16" belowBase="0" code="1264" height="16" selected="true" startX="0" startY="16" width="11" xAdvance="11">CQEgAAAMBMGIIYwRAyAsBwBgGAYDgA==</glyph>
    <glyph aboveBase="13" belowBase="4" code="1265" height="17" selected="true" startX="0" startY="13" width="9" xAdvance="9">JBIAAAwSGQzEJhoFA4GAwEBg4AA=</glyph>
    <glyph aboveBase="16" belowBase="0" code="1266" height="16" selected="true" startX="0" startY="16" width="11" xAdvance="11">BoGwJAAMBMGIIYwRAyAsBwBgGAYDgA==</glyph>
    <glyph aboveBase="13" belowBase="4" code="1267" height="17" selected="true" startX="0" startY="13" width="9" xAdvance="9">DQ2EgAwSGQzEJhoFA4GAwEBg4AA=</glyph>
    <glyph aboveBase="16" belowBase="0" code="1268" height="16" selected="true" startX="1" startY="16" width="9" xAdvance="12">EgkAAAwOBwOBwOBY59AIBAIB</glyph>
    <glyph aboveBase="13" belowBase="0" code="1269" height="13" selected="true" startX="1" startY="13" width="8" xAdvance="10">JCQAAMPDw8PHewMDAw==</glyph>
    <glyph aboveBase="12" belowBase="3" code="1270" height="15" selected="true" startX="2" startY="12" width="7" xAdvance="9">/wIECBAgQIECBgQIEAA=</glyph>
    <glyph aboveBase="9" belowBase="3" code="1271" height="12" selected="true" startX="1" startY="9" width="6" xAdvance="7">/wwwwwww4III</glyph>
    <glyph aboveBase="16" belowBase="0" code="1272" height="16" selected="true" startX="2" startY="16" width="11" xAdvance="14">EgJAAAAIBwDgHAOAf44ZwTgnBOGf4w==</glyph>
    <glyph aboveBase="13" belowBase="0" code="1273" height="13" selected="true" startX="1" startY="13" width="11" xAdvance="13">CQEgAAAMB4DwHgP+eG8N4b/m</glyph>
    <glyph aboveBase="12" belowBase="4" code="1274" height="16" selected="true" startX="0" startY="12" width="9" xAdvance="9">P5AIBAIBA/hAIBAIBgEAgEDg</glyph>
    <glyph aboveBase="9" belowBase="3" code="1275" height="12" selected="true" startX="0" startY="9" width="7" xAdvance="7">fsGDD8wYMHAgQ4A=</glyph>
    <glyph aboveBase="12" belowBase="3" code="1276" height="15" selected="true" startX="0" startY="12" width="10" xAdvance="11">QJhCMEgeAwDAWDMIRBsDAEAQHA==</glyph>
    <glyph aboveBase="9" belowBase="3" code="1277" height="12" selected="true" startX="0" startY="9" width="9" xAdvance="9">QxENg4CAoNjEQYBAIHA=</glyph>
    <glyph aboveBase="12" belowBase="0" code="1278" height="12" selected="true" startX="0" startY="12" width="10" xAdvance="10">QJhDMEgcH+HASDMIRBsC</glyph>
  </glyphs>
</embeddedFont>
